{"schema":{"fields":[{"name":"index","type":"integer"},{"name":"term","type":"string"},{"name":"probability","type":"number"},{"name":"topic","type":"integer"}],"primaryKey":["index"],"pandas_version":"1.4.0"},"data":[{"index":0,"term":"i\u2019m","probability":0.00083097,"topic":0},{"index":1,"term":"e","probability":0.0006340305,"topic":0},{"index":2,"term":"facts","probability":0.0006307692,"topic":0},{"index":3,"term":"set","probability":0.0005891954,"topic":0},{"index":4,"term":"well,","probability":0.0004782421,"topic":0},{"index":5,"term":"sorry","probability":0.0004419618,"topic":0},{"index":6,"term":"b","probability":0.0004169491,"topic":0},{"index":7,"term":"1979.","probability":0.0003965522,"topic":0},{"index":8,"term":"view","probability":0.0003962033,"topic":0},{"index":9,"term":"everybody.","probability":0.0003798602,"topic":0},{"index":10,"term":"well","probability":0.0018215199,"topic":1},{"index":11,"term":"played","probability":0.0003171342,"topic":1},{"index":12,"term":"truth","probability":0.0003154688,"topic":1},{"index":13,"term":"anime_irl","probability":0.0003089233,"topic":1},{"index":14,"term":"trick","probability":0.0002991301,"topic":1},{"index":15,"term":"lord","probability":0.0002943653,"topic":1},{"index":16,"term":"tesla","probability":0.0002811826,"topic":1},{"index":17,"term":"experience","probability":0.0002683029,"topic":1},{"index":18,"term":"bass","probability":0.0002471141,"topic":1},{"index":19,"term":"ackwards","probability":0.0002440297,"topic":1},{"index":20,"term":"big","probability":0.0024778494,"topic":2},{"index":21,"term":"people","probability":0.002175623,"topic":2},{"index":22,"term":"got","probability":0.0021754013,"topic":2},{"index":23,"term":"irl","probability":0.0017468599,"topic":2},{"index":24,"term":"found","probability":0.001552246,"topic":2},{"index":25,"term":"trump","probability":0.0013434205,"topic":2},{"index":26,"term":"huskies","probability":0.0013086413,"topic":2},{"index":27,"term":"actually","probability":0.0013044219,"topic":2},{"index":28,"term":"best","probability":0.0012641016,"topic":2},{"index":29,"term":"always","probability":0.0011944508,"topic":2},{"index":30,"term":"kitty","probability":0.0003246981,"topic":3},{"index":31,"term":"apologize","probability":0.000298753,"topic":3},{"index":32,"term":"local","probability":0.0002741482,"topic":3},{"index":33,"term":"duolingo,","probability":0.0002688019,"topic":3},{"index":34,"term":"grim","probability":0.0002586219,"topic":3},{"index":35,"term":"czar","probability":0.0002564314,"topic":3},{"index":36,"term":"communication","probability":0.0002557472,"topic":3},{"index":37,"term":"tom","probability":0.0002556367,"topic":3},{"index":38,"term":"reaper","probability":0.0002526544,"topic":3},{"index":39,"term":"escape","probability":0.0002508691,"topic":3},{"index":40,"term":"like","probability":0.0042623991,"topic":4},{"index":41,"term":"new","probability":0.0033719383,"topic":4},{"index":42,"term":"til","probability":0.002825887,"topic":4},{"index":43,"term":"one","probability":0.0026575218,"topic":4},{"index":44,"term":"old","probability":0.0025592343,"topic":4},{"index":45,"term":"time","probability":0.0024556465,"topic":4},{"index":46,"term":"made","probability":0.0023867135,"topic":4},{"index":47,"term":"\ud83d\udd25","probability":0.0023700257,"topic":4},{"index":48,"term":"would","probability":0.0021533032,"topic":4},{"index":49,"term":"years","probability":0.0019607312,"topic":4},{"index":50,"term":"sad","probability":0.0005240128,"topic":5},{"index":51,"term":"hard","probability":0.0004851744,"topic":5},{"index":52,"term":":(","probability":0.000453214,"topic":5},{"index":53,"term":"titles","probability":0.0004177412,"topic":5},{"index":54,"term":"101","probability":0.0003802466,"topic":5},{"index":55,"term":"python","probability":0.0003490747,"topic":5},{"index":56,"term":"cobra","probability":0.0003476915,"topic":5},{"index":57,"term":"dies","probability":0.0003457474,"topic":5},{"index":58,"term":"sbeve","probability":0.0003427035,"topic":5},{"index":59,"term":"airport","probability":0.0003417336,"topic":5},{"index":60,"term":"psbattle:","probability":0.0020404751,"topic":6},{"index":61,"term":"2meirl4meirl","probability":0.0019879274,"topic":6},{"index":62,"term":"oh","probability":0.0012252735,"topic":6},{"index":63,"term":"[homemade]","probability":0.0008760875,"topic":6},{"index":64,"term":"guy","probability":0.0008514216,"topic":6},{"index":65,"term":"james","probability":0.0006442776,"topic":6},{"index":66,"term":"pewdiepie","probability":0.000590154,"topic":6},{"index":67,"term":"god","probability":0.0005546579,"topic":6},{"index":68,"term":"name","probability":0.0005458597,"topic":6},{"index":69,"term":"amazing","probability":0.0004626569,"topic":6},{"index":70,"term":"want","probability":0.0015469584,"topic":7},{"index":71,"term":"library","probability":0.0006485129,"topic":7},{"index":72,"term":"help","probability":0.000547144,"topic":7},{"index":73,"term":"yes","probability":0.0005392087,"topic":7},{"index":74,"term":"one","probability":0.0004323568,"topic":7},{"index":75,"term":"record","probability":0.0004314153,"topic":7},{"index":76,"term":"age","probability":0.0004258233,"topic":7},{"index":77,"term":"group","probability":0.0004234217,"topic":7},{"index":78,"term":"suicide","probability":0.000347064,"topic":7},{"index":79,"term":"gatekeeping","probability":0.0003191406,"topic":7},{"index":80,"term":"cat","probability":0.0025459587,"topic":8},{"index":81,"term":"hmmm","probability":0.0025310957,"topic":8},{"index":82,"term":"little","probability":0.0024214299,"topic":8},{"index":83,"term":"get","probability":0.0022276489,"topic":8},{"index":84,"term":"see","probability":0.0020345156,"topic":8},{"index":85,"term":"true","probability":0.0010901245,"topic":8},{"index":86,"term":"love","probability":0.0010241366,"topic":8},{"index":87,"term":"-","probability":0.0009600497,"topic":8},{"index":88,"term":"invest","probability":0.0009460401,"topic":8},{"index":89,"term":"think","probability":0.000945564,"topic":8},{"index":90,"term":"good","probability":0.0027831588,"topic":9},{"index":91,"term":"never","probability":0.0018535837,"topic":9},{"index":92,"term":"way","probability":0.0016754997,"topic":9},{"index":93,"term":"one","probability":0.0014826418,"topic":9},{"index":94,"term":"give","probability":0.0014057369,"topic":9},{"index":95,"term":"man","probability":0.001389023,"topic":9},{"index":96,"term":"need","probability":0.0013387744,"topic":9},{"index":97,"term":"first","probability":0.0013334635,"topic":9},{"index":98,"term":"wholesome","probability":0.0013025036,"topic":9},{"index":99,"term":"making","probability":0.0011999774,"topic":9}]}