{"schema":{"fields":[{"name":"index","type":"integer"},{"name":"term","type":"string"},{"name":"probability","type":"number"},{"name":"topic","type":"integer"}],"primaryKey":["index"],"pandas_version":"1.4.0"},"data":[{"index":0,"term":"open","probability":0.0007066224,"topic":0},{"index":1,"term":"face","probability":0.0006889655,"topic":0},{"index":2,"term":"rock","probability":0.0005166648,"topic":0},{"index":3,"term":"peruvian","probability":0.000504607,"topic":0},{"index":4,"term":"earthquake","probability":0.0004674356,"topic":0},{"index":5,"term":"death","probability":0.0004605914,"topic":0},{"index":6,"term":"prison","probability":0.0004493275,"topic":0},{"index":7,"term":"found","probability":0.0004284227,"topic":0},{"index":8,"term":"|","probability":0.0003902751,"topic":0},{"index":9,"term":"earth","probability":0.0003787512,"topic":0},{"index":10,"term":"experience","probability":0.0010968163,"topic":1},{"index":11,"term":"vs","probability":0.0009424604,"topic":1},{"index":12,"term":"glass","probability":0.0007351274,"topic":1},{"index":13,"term":"day","probability":0.0006663638,"topic":1},{"index":14,"term":"man","probability":0.0006566078,"topic":1},{"index":15,"term":"vr","probability":0.0006150627,"topic":1},{"index":16,"term":"old","probability":0.0005419495,"topic":1},{"index":17,"term":"thought","probability":0.0005385711,"topic":1},{"index":18,"term":"meanwhile","probability":0.000529838,"topic":1},{"index":19,"term":"game","probability":0.0005196421,"topic":1},{"index":20,"term":"trump","probability":0.0066631849,"topic":2},{"index":21,"term":"new","probability":0.0042697237,"topic":2},{"index":22,"term":null,"probability":0.0040751618,"topic":2},{"index":23,"term":"one","probability":0.0040462041,"topic":2},{"index":24,"term":"til","probability":0.0036199507,"topic":2},{"index":25,"term":"like","probability":0.0031783322,"topic":2},{"index":26,"term":"first","probability":0.0030103927,"topic":2},{"index":27,"term":"donald","probability":0.0026440625,"topic":2},{"index":28,"term":"people","probability":0.0024992857,"topic":2},{"index":29,"term":"years","probability":0.002491497,"topic":2},{"index":30,"term":"use","probability":0.0005222728,"topic":3},{"index":31,"term":"day","probability":0.0005062361,"topic":3},{"index":32,"term":"ice","probability":0.0004341808,"topic":3},{"index":33,"term":"inside","probability":0.0004130415,"topic":3},{"index":34,"term":"superb","probability":0.0004024065,"topic":3},{"index":35,"term":"ult","probability":0.0003786795,"topic":3},{"index":36,"term":"anniversary","probability":0.0003500727,"topic":3},{"index":37,"term":"throw","probability":0.0003397807,"topic":3},{"index":38,"term":"25th","probability":0.0003333229,"topic":3},{"index":39,"term":"proposal","probability":0.0003279242,"topic":3},{"index":40,"term":"dont","probability":0.0019831674,"topic":4},{"index":41,"term":"ever","probability":0.0018235625,"topic":4},{"index":42,"term":"team","probability":0.0017096098,"topic":4},{"index":43,"term":"play","probability":0.0016785936,"topic":4},{"index":44,"term":"finally","probability":0.0015468579,"topic":4},{"index":45,"term":"long","probability":0.0010296943,"topic":4},{"index":46,"term":"best","probability":0.0009811662,"topic":4},{"index":47,"term":"xbox","probability":0.000738956,"topic":4},{"index":48,"term":"anime_irl","probability":0.0006803834,"topic":4},{"index":49,"term":"blood","probability":0.0006704423,"topic":4},{"index":50,"term":"dream","probability":0.0003585758,"topic":5},{"index":51,"term":"seeds","probability":0.0003272926,"topic":5},{"index":52,"term":"crazy","probability":0.0002991027,"topic":5},{"index":53,"term":"small","probability":0.000297591,"topic":5},{"index":54,"term":"la","probability":0.0002892116,"topic":5},{"index":55,"term":"x","probability":0.0002660436,"topic":5},{"index":56,"term":"test","probability":0.0002629209,"topic":5},{"index":57,"term":"victories","probability":0.00026006,"topic":5},{"index":58,"term":"starbucks","probability":0.0002524113,"topic":5},{"index":59,"term":"baggage","probability":0.0002486116,"topic":5},{"index":60,"term":"red","probability":0.0011566453,"topic":6},{"index":61,"term":"meirl","probability":0.000867763,"topic":6},{"index":62,"term":"wild","probability":0.0006907512,"topic":6},{"index":63,"term":"need","probability":0.0006338921,"topic":6},{"index":64,"term":"wall","probability":0.0006095806,"topic":6},{"index":65,"term":"legend","probability":0.0005564398,"topic":6},{"index":66,"term":"zelda","probability":0.0005560896,"topic":6},{"index":67,"term":"breath","probability":0.0005478592,"topic":6},{"index":68,"term":"apple","probability":0.0005215565,"topic":6},{"index":69,"term":"frozen","probability":0.0005047309,"topic":6},{"index":70,"term":"baby","probability":0.0017088336,"topic":7},{"index":71,"term":"(xpost","probability":0.001543414,"topic":7},{"index":72,"term":"got","probability":0.0013902904,"topic":7},{"index":73,"term":"right","probability":0.0011054536,"topic":7},{"index":74,"term":"way","probability":0.0010909631,"topic":7},{"index":75,"term":"thanks","probability":0.0010861254,"topic":7},{"index":76,"term":")","probability":0.0010558756,"topic":7},{"index":77,"term":"home","probability":0.0010410297,"topic":7},{"index":78,"term":"gets","probability":0.0010066229,"topic":7},{"index":79,"term":"game","probability":0.0009546594,"topic":7},{"index":80,"term":"irl","probability":0.0057749097,"topic":8},{"index":81,"term":"like","probability":0.003067825,"topic":8},{"index":82,"term":"looks","probability":0.002018193,"topic":8},{"index":83,"term":"&","probability":0.0009667396,"topic":8},{"index":84,"term":"using","probability":0.0007770891,"topic":8},{"index":85,"term":"doesnt","probability":0.0007399992,"topic":8},{"index":86,"term":"liquid","probability":0.000723423,"topic":8},{"index":87,"term":"[homemade]","probability":0.0006883469,"topic":8},{"index":88,"term":"wife","probability":0.00059312,"topic":8},{"index":89,"term":"cats","probability":0.0005922488,"topic":8},{"index":90,"term":"me_irl","probability":0.0029408515,"topic":9},{"index":91,"term":"ice","probability":0.0010910972,"topic":9},{"index":92,"term":"hold","probability":0.0006310247,"topic":9},{"index":93,"term":"joke","probability":0.0006041615,"topic":9},{"index":94,"term":"human","probability":0.000487231,"topic":9},{"index":95,"term":"used","probability":0.0004745686,"topic":9},{"index":96,"term":"obama","probability":0.0004567097,"topic":9},{"index":97,"term":"party","probability":0.0004540676,"topic":9},{"index":98,"term":"chelsea","probability":0.0004382445,"topic":9},{"index":99,"term":"commutes","probability":0.0004349285,"topic":9}]}