{"schema":{"fields":[{"name":"index","type":"integer"},{"name":"term","type":"string"},{"name":"probability","type":"number"},{"name":"topic","type":"integer"}],"primaryKey":["index"],"pandas_version":"1.4.0"},"data":[{"index":0,"term":"level","probability":0.0004188157,"topic":0},{"index":1,"term":"bubble","probability":0.0003721993,"topic":0},{"index":2,"term":"lost","probability":0.0003364906,"topic":0},{"index":3,"term":"2014","probability":0.0003274428,"topic":0},{"index":4,"term":"minute","probability":0.0003214279,"topic":0},{"index":5,"term":"myself,","probability":0.0002864946,"topic":0},{"index":6,"term":"media","probability":0.0002823027,"topic":0},{"index":7,"term":"paper,","probability":0.0002802134,"topic":0},{"index":8,"term":"alari,","probability":0.000279037,"topic":0},{"index":9,"term":"mixed","probability":0.0002764328,"topic":0},{"index":10,"term":"got","probability":0.0006297221,"topic":1},{"index":11,"term":"cosplay","probability":0.0004888194,"topic":1},{"index":12,"term":"actually","probability":0.00042072,"topic":1},{"index":13,"term":"expectations","probability":0.0003003353,"topic":1},{"index":14,"term":"place","probability":0.0002925449,"topic":1},{"index":15,"term":"potato","probability":0.0002784591,"topic":1},{"index":16,"term":"school","probability":0.0002771953,"topic":1},{"index":17,"term":"episode","probability":0.0002737552,"topic":1},{"index":18,"term":"oc","probability":0.0002574881,"topic":1},{"index":19,"term":"reality","probability":0.0002450999,"topic":1},{"index":20,"term":"trump","probability":0.00663559,"topic":2},{"index":21,"term":"til","probability":0.0028043575,"topic":2},{"index":22,"term":"donald","probability":0.0025742676,"topic":2},{"index":23,"term":"russian","probability":0.0019361518,"topic":2},{"index":24,"term":"russia","probability":0.0015885616,"topic":2},{"index":25,"term":"white","probability":0.0015196122,"topic":2},{"index":26,"term":"house","probability":0.001518651,"topic":2},{"index":27,"term":"day","probability":0.0013401863,"topic":2},{"index":28,"term":"made","probability":0.0012965744,"topic":2},{"index":29,"term":"2","probability":0.0012380331,"topic":2},{"index":30,"term":"e","probability":0.0008124492,"topic":3},{"index":31,"term":"c","probability":0.0005580744,"topic":3},{"index":32,"term":"b","probability":0.0005194996,"topic":3},{"index":33,"term":"hate","probability":0.0003795763,"topic":3},{"index":34,"term":"\ud83d\udd25","probability":0.0003638717,"topic":3},{"index":35,"term":"seeing","probability":0.0003476856,"topic":3},{"index":36,"term":"u","probability":0.0003266365,"topic":3},{"index":37,"term":"h","probability":0.0003100572,"topic":3},{"index":38,"term":"r","probability":0.0003096647,"topic":3},{"index":39,"term":"p","probability":0.0003087223,"topic":3},{"index":40,"term":"new","probability":0.0037277802,"topic":4},{"index":41,"term":"like","probability":0.003261599,"topic":4},{"index":42,"term":"one","probability":0.0030766818,"topic":4},{"index":43,"term":"-","probability":0.0027123794,"topic":4},{"index":44,"term":"get","probability":0.0023747393,"topic":4},{"index":45,"term":"dog","probability":0.0022580987,"topic":4},{"index":46,"term":"first","probability":0.0022038171,"topic":4},{"index":47,"term":"people","probability":0.0021739003,"topic":4},{"index":48,"term":"time","probability":0.0020254872,"topic":4},{"index":49,"term":"til","probability":0.0019559717,"topic":4},{"index":50,"term":"step","probability":0.0006602888,"topic":5},{"index":51,"term":"meirl","probability":0.0005132724,"topic":5},{"index":52,"term":"tree","probability":0.000507905,"topic":5},{"index":53,"term":"big","probability":0.0004820185,"topic":5},{"index":54,"term":"steal","probability":0.000353002,"topic":5},{"index":55,"term":"pepsi","probability":0.0003461192,"topic":5},{"index":56,"term":"tell","probability":0.0003251319,"topic":5},{"index":57,"term":"vs","probability":0.0003104848,"topic":5},{"index":58,"term":"cry","probability":0.000284831,"topic":5},{"index":59,"term":"comic","probability":0.0002824549,"topic":5},{"index":60,"term":"irl","probability":0.004550494,"topic":6},{"index":61,"term":"found","probability":0.0005954605,"topic":6},{"index":62,"term":"make","probability":0.0005734651,"topic":6},{"index":63,"term":"want","probability":0.0005298609,"topic":6},{"index":64,"term":"iron","probability":0.0004553303,"topic":6},{"index":65,"term":"fight","probability":0.0004159811,"topic":6},{"index":66,"term":"faces","probability":0.000399725,"topic":6},{"index":67,"term":"fish","probability":0.0003889099,"topic":6},{"index":68,"term":"fist","probability":0.0003651052,"topic":6},{"index":69,"term":"aswell","probability":0.0003513638,"topic":6},{"index":70,"term":"work","probability":0.0006259257,"topic":7},{"index":71,"term":"30","probability":0.00048432,"topic":7},{"index":72,"term":"dead","probability":0.0004652478,"topic":7},{"index":73,"term":"life","probability":0.0003825673,"topic":7},{"index":74,"term":"creatures","probability":0.0003362627,"topic":7},{"index":75,"term":"job","probability":0.0003342608,"topic":7},{"index":76,"term":"designer","probability":0.000310818,"topic":7},{"index":77,"term":"attempt","probability":0.0003004105,"topic":7},{"index":78,"term":"stay","probability":0.0002965048,"topic":7},{"index":79,"term":"you!","probability":0.0002883752,"topic":7},{"index":80,"term":"one","probability":0.001852797,"topic":8},{"index":81,"term":"man","probability":0.0013187855,"topic":8},{"index":82,"term":"stop","probability":0.0011267298,"topic":8},{"index":83,"term":"love","probability":0.0008696413,"topic":8},{"index":84,"term":"beautiful","probability":0.000705676,"topic":8},{"index":85,"term":"switch","probability":0.0006610147,"topic":8},{"index":86,"term":"two","probability":0.0006582959,"topic":8},{"index":87,"term":"first","probability":0.0006469248,"topic":8},{"index":88,"term":"got","probability":0.0006313008,"topic":8},{"index":89,"term":"would","probability":0.000616346,"topic":8},{"index":90,"term":"me_irl","probability":0.0016552237,"topic":9},{"index":91,"term":"china","probability":0.0005163797,"topic":9},{"index":92,"term":"girl","probability":0.0005080121,"topic":9},{"index":93,"term":"road","probability":0.0004584675,"topic":9},{"index":94,"term":"ever","probability":0.0004144846,"topic":9},{"index":95,"term":"team","probability":0.0004063838,"topic":9},{"index":96,"term":"matrix","probability":0.0003707315,"topic":9},{"index":97,"term":"taken","probability":0.0003482252,"topic":9},{"index":98,"term":"brown","probability":0.0003434167,"topic":9},{"index":99,"term":"little","probability":0.0003312324,"topic":9}]}