{"schema":{"fields":[{"name":"index","type":"integer"},{"name":"term","type":"string"},{"name":"probability","type":"number"},{"name":"topic","type":"integer"}],"primaryKey":["index"],"pandas_version":"1.4.0"},"data":[{"index":0,"term":"love","probability":0.0017756297,"topic":0},{"index":1,"term":"come","probability":0.00082407,"topic":0},{"index":2,"term":"seems","probability":0.0004637452,"topic":0},{"index":3,"term":"beast","probability":0.0004533146,"topic":0},{"index":4,"term":"left","probability":0.0003932867,"topic":0},{"index":5,"term":"cows","probability":0.0003787658,"topic":0},{"index":6,"term":"legit","probability":0.0003590952,"topic":0},{"index":7,"term":"true","probability":0.000347387,"topic":0},{"index":8,"term":"per","probability":0.0003378219,"topic":0},{"index":9,"term":"exit","probability":0.0003307835,"topic":0},{"index":10,"term":"star","probability":0.0012839487,"topic":1},{"index":11,"term":"ama","probability":0.001111861,"topic":1},{"index":12,"term":"united","probability":0.0010826724,"topic":1},{"index":13,"term":"2015","probability":0.0009909109,"topic":1},{"index":14,"term":"states","probability":0.000981425,"topic":1},{"index":15,"term":"train","probability":0.0008440021,"topic":1},{"index":16,"term":"til","probability":0.0008318875,"topic":1},{"index":17,"term":"saw","probability":0.0008028894,"topic":1},{"index":18,"term":"behind","probability":0.0007326873,"topic":1},{"index":19,"term":"got","probability":0.0006780737,"topic":1},{"index":20,"term":"new","probability":0.0044579435,"topic":2},{"index":21,"term":"one","probability":0.0042869588,"topic":2},{"index":22,"term":"like","probability":0.0040828623,"topic":2},{"index":23,"term":"im","probability":0.0037300704,"topic":2},{"index":24,"term":"time","probability":0.0032735458,"topic":2},{"index":25,"term":"day","probability":0.0031512895,"topic":2},{"index":26,"term":"today","probability":0.0031495389,"topic":2},{"index":27,"term":"get","probability":0.0031246217,"topic":2},{"index":28,"term":null,"probability":0.0028809627,"topic":2},{"index":29,"term":"first","probability":0.0028800604,"topic":2},{"index":30,"term":"blue","probability":0.000695183,"topic":3},{"index":31,"term":"&","probability":0.0006398312,"topic":3},{"index":32,"term":"nasa","probability":0.0005705593,"topic":3},{"index":33,"term":"jesus","probability":0.000546695,"topic":3},{"index":34,"term":"attack","probability":0.0004445882,"topic":3},{"index":35,"term":"competition","probability":0.0003507557,"topic":3},{"index":36,"term":"international","probability":0.0003491104,"topic":3},{"index":37,"term":"article","probability":0.0003474106,"topic":3},{"index":38,"term":"africa","probability":0.0003444261,"topic":3},{"index":39,"term":"results","probability":0.0003323402,"topic":3},{"index":40,"term":null,"probability":0.0025144844,"topic":4},{"index":41,"term":"game","probability":0.0022663632,"topic":4},{"index":42,"term":"people","probability":0.0016873851,"topic":4},{"index":43,"term":"trying","probability":0.0015131982,"topic":4},{"index":44,"term":"mrw","probability":0.0013060271,"topic":4},{"index":45,"term":"wife","probability":0.0012948776,"topic":4},{"index":46,"term":"vs","probability":0.0011605007,"topic":4},{"index":47,"term":"thread","probability":0.001016837,"topic":4},{"index":48,"term":"reddit","probability":0.0009152646,"topic":4},{"index":49,"term":"much","probability":0.0008903042,"topic":4},{"index":50,"term":"kitty","probability":0.001157332,"topic":5},{"index":51,"term":"team","probability":0.0007860057,"topic":5},{"index":52,"term":"selfie","probability":0.0006219777,"topic":5},{"index":53,"term":"women","probability":0.0005666367,"topic":5},{"index":54,"term":"korea","probability":0.0005120407,"topic":5},{"index":55,"term":"north","probability":0.0004108365,"topic":5},{"index":56,"term":"evil","probability":0.0004066961,"topic":5},{"index":57,"term":"jimmy","probability":0.0004026274,"topic":5},{"index":58,"term":"encounter","probability":0.0003964316,"topic":5},{"index":59,"term":"fallon","probability":0.0003549515,"topic":5},{"index":60,"term":"get","probability":0.001065662,"topic":6},{"index":61,"term":"right","probability":0.0009716625,"topic":6},{"index":62,"term":"great","probability":0.0008853499,"topic":6},{"index":63,"term":"free","probability":0.0007924654,"topic":6},{"index":64,"term":"francis","probability":0.0006181593,"topic":6},{"index":65,"term":"art","probability":0.0005277093,"topic":6},{"index":66,"term":"new","probability":0.0005030634,"topic":6},{"index":67,"term":"sun","probability":0.000486475,"topic":6},{"index":68,"term":"classy","probability":0.0004796195,"topic":6},{"index":69,"term":"rules","probability":0.0004769663,"topic":6},{"index":70,"term":"one","probability":0.0015819111,"topic":7},{"index":71,"term":"world","probability":0.0015147049,"topic":7},{"index":72,"term":"oh","probability":0.0014547144,"topic":7},{"index":73,"term":"state","probability":0.0013455053,"topic":7},{"index":74,"term":"hey","probability":0.0012586371,"topic":7},{"index":75,"term":"real","probability":0.0012008176,"topic":7},{"index":76,"term":"looks","probability":0.0011329736,"topic":7},{"index":77,"term":"life","probability":0.0010797635,"topic":7},{"index":78,"term":"top","probability":0.0010681104,"topic":7},{"index":79,"term":"office","probability":0.0010130814,"topic":7},{"index":80,"term":"til","probability":0.0045413668,"topic":8},{"index":81,"term":"little","probability":0.0025424797,"topic":8},{"index":82,"term":"year","probability":0.0018336984,"topic":8},{"index":83,"term":"man","probability":0.0017168909,"topic":8},{"index":84,"term":"years","probability":0.0016291123,"topic":8},{"index":85,"term":"old","probability":0.0015986054,"topic":8},{"index":86,"term":"never","probability":0.0013743745,"topic":8},{"index":87,"term":"2","probability":0.0013349331,"topic":8},{"index":88,"term":"like","probability":0.0012585342,"topic":8},{"index":89,"term":"made","probability":0.0011950978,"topic":8},{"index":90,"term":"text","probability":0.0005044597,"topic":9},{"index":91,"term":"upcoming","probability":0.0004018399,"topic":9},{"index":92,"term":"laser","probability":0.0003639981,"topic":9},{"index":93,"term":"dying","probability":0.0003466636,"topic":9},{"index":94,"term":"similar","probability":0.0003455187,"topic":9},{"index":95,"term":"net","probability":0.0003449521,"topic":9},{"index":96,"term":"dub","probability":0.0003418947,"topic":9},{"index":97,"term":"costs","probability":0.0003339926,"topic":9},{"index":98,"term":"season","probability":0.0003322257,"topic":9},{"index":99,"term":"longer","probability":0.0003096562,"topic":9}]}