{"schema":{"fields":[{"name":"index","type":"integer"},{"name":"term","type":"string"},{"name":"probability","type":"number"},{"name":"topic","type":"integer"}],"primaryKey":["index"],"pandas_version":"1.4.0"},"data":[{"index":0,"term":"duck","probability":0.0004811304,"topic":0},{"index":1,"term":"swimming","probability":0.0004277464,"topic":0},{"index":2,"term":"yap","probability":0.0004088122,"topic":0},{"index":3,"term":"theory","probability":0.0004011162,"topic":0},{"index":4,"term":"samurai","probability":0.0003595889,"topic":0},{"index":5,"term":"rip","probability":0.000339505,"topic":0},{"index":6,"term":"drink","probability":0.000323974,"topic":0},{"index":7,"term":"pizza","probability":0.0003109434,"topic":0},{"index":8,"term":"laps","probability":0.0003109208,"topic":0},{"index":9,"term":"forest","probability":0.0002964289,"topic":0},{"index":10,"term":"til","probability":0.0015267074,"topic":1},{"index":11,"term":null,"probability":0.0010486191,"topic":1},{"index":12,"term":"get","probability":0.0010203893,"topic":1},{"index":13,"term":"family","probability":0.0010202937,"topic":1},{"index":14,"term":"year","probability":0.0009651932,"topic":1},{"index":15,"term":"batman","probability":0.0006893628,"topic":1},{"index":16,"term":"good","probability":0.0006499429,"topic":1},{"index":17,"term":"student","probability":0.0006365183,"topic":1},{"index":18,"term":"mind","probability":0.0006133074,"topic":1},{"index":19,"term":"logo","probability":0.0006008459,"topic":1},{"index":20,"term":"one","probability":0.0050809154,"topic":2},{"index":21,"term":"like","probability":0.0044017937,"topic":2},{"index":22,"term":"til","probability":0.0043864145,"topic":2},{"index":23,"term":null,"probability":0.0036012483,"topic":2},{"index":24,"term":"day","probability":0.0031496253,"topic":2},{"index":25,"term":"time","probability":0.0031133216,"topic":2},{"index":26,"term":"guy","probability":0.0030437793,"topic":2},{"index":27,"term":"made","probability":0.0029960243,"topic":2},{"index":28,"term":"new","probability":0.0027502568,"topic":2},{"index":29,"term":"today","probability":0.0027334576,"topic":2},{"index":30,"term":"always","probability":0.0005641409,"topic":3},{"index":31,"term":"mike","probability":0.0005334417,"topic":3},{"index":32,"term":"cool","probability":0.0005148499,"topic":3},{"index":33,"term":"flying","probability":0.0004639092,"topic":3},{"index":34,"term":"jetstream","probability":0.0003611677,"topic":3},{"index":35,"term":"rainbow","probability":0.0003594363,"topic":3},{"index":36,"term":"fish","probability":0.0003501509,"topic":3},{"index":37,"term":"escape","probability":0.0003497038,"topic":3},{"index":38,"term":"hamster","probability":0.0003163009,"topic":3},{"index":39,"term":"animals","probability":0.0003152871,"topic":3},{"index":40,"term":"im","probability":0.0026583801,"topic":4},{"index":41,"term":"going","probability":0.0018211289,"topic":4},{"index":42,"term":"night","probability":0.0010769516,"topic":4},{"index":43,"term":"whats","probability":0.0010593148,"topic":4},{"index":44,"term":"last","probability":0.0009313322,"topic":4},{"index":45,"term":"goes","probability":0.0008346033,"topic":4},{"index":46,"term":"get","probability":0.0008013897,"topic":4},{"index":47,"term":"faces","probability":0.0007965429,"topic":4},{"index":48,"term":"kill","probability":0.000790847,"topic":4},{"index":49,"term":"poor","probability":0.0007701943,"topic":4},{"index":50,"term":"michael","probability":0.0006774874,"topic":5},{"index":51,"term":"happened","probability":0.000473315,"topic":5},{"index":52,"term":"[no","probability":0.0004637395,"topic":5},{"index":53,"term":"noticed","probability":0.0004452836,"topic":5},{"index":54,"term":"spoilers]","probability":0.0004133019,"topic":5},{"index":55,"term":"argument","probability":0.0004132276,"topic":5},{"index":56,"term":"ageold","probability":0.0004018955,"topic":5},{"index":57,"term":"drafted","probability":0.0003702344,"topic":5},{"index":58,"term":"sam","probability":0.0003654083,"topic":5},{"index":59,"term":"cup","probability":0.000358174,"topic":5},{"index":60,"term":"stop","probability":0.0012804998,"topic":6},{"index":61,"term":"dont","probability":0.0012443294,"topic":6},{"index":62,"term":"way","probability":0.0009615815,"topic":6},{"index":63,"term":"truck","probability":0.0009374975,"topic":6},{"index":64,"term":"sign","probability":0.0009173748,"topic":6},{"index":65,"term":"x","probability":0.0007764423,"topic":6},{"index":66,"term":"til","probability":0.0007371598,"topic":6},{"index":67,"term":"post","probability":0.0006951209,"topic":6},{"index":68,"term":"couple","probability":0.0006671771,"topic":6},{"index":69,"term":"death","probability":0.0006658133,"topic":6},{"index":70,"term":"new","probability":0.0029853415,"topic":7},{"index":71,"term":"cat","probability":0.0026966438,"topic":7},{"index":72,"term":"first","probability":0.0025387057,"topic":7},{"index":73,"term":"ama","probability":0.0018696529,"topic":7},{"index":74,"term":"oh","probability":0.0016225424,"topic":7},{"index":75,"term":"[xpost","probability":0.0014573123,"topic":7},{"index":76,"term":"baby","probability":0.001260632,"topic":7},{"index":77,"term":"works","probability":0.0011373504,"topic":7},{"index":78,"term":"friends","probability":0.000988395,"topic":7},{"index":79,"term":"cant","probability":0.0009653857,"topic":7},{"index":80,"term":"man","probability":0.0037891535,"topic":8},{"index":81,"term":"makes","probability":0.0017782965,"topic":8},{"index":82,"term":"today","probability":0.0016518465,"topic":8},{"index":83,"term":"love","probability":0.001651076,"topic":8},{"index":84,"term":"reddit","probability":0.0013046763,"topic":8},{"index":85,"term":"found","probability":0.0011774366,"topic":8},{"index":86,"term":"years","probability":0.0010017164,"topic":8},{"index":87,"term":"child","probability":0.0009968802,"topic":8},{"index":88,"term":"tattoo","probability":0.0009617376,"topic":8},{"index":89,"term":"days","probability":0.000950906,"topic":8},{"index":90,"term":"god","probability":0.0010270818,"topic":9},{"index":91,"term":"yes","probability":0.0006699394,"topic":9},{"index":92,"term":"jackson","probability":0.0006224254,"topic":9},{"index":93,"term":"freedom","probability":0.0005604876,"topic":9},{"index":94,"term":"face","probability":0.0005534129,"topic":9},{"index":95,"term":"wait","probability":0.0005017305,"topic":9},{"index":96,"term":"l","probability":0.0004950785,"topic":9},{"index":97,"term":"samuel","probability":0.000489555,"topic":9},{"index":98,"term":"stupid","probability":0.0004289065,"topic":9},{"index":99,"term":"cloud","probability":0.0003721767,"topic":9}]}